expyfp/__init__.py
expyfp/chaos.py
expyfp/eso_int.py
expyfp/input_validation.py
expyfp/meta_programming.py
expyfp/meta_utility.py
expyfp/random_decorators.py
expyfp/unit_test_decorators.py
expyfp-0.2.4.dist-info/METADATA
expyfp-0.2.4.dist-info/WHEEL
expyfp-0.2.4.dist-info/RECORD
