Metadata-Version: 2.1
Name: expyfp
Version: 0.2.4
Summary: merging previous projects into this one for ease of use & sharing, heavy WIP
Author: lone_druid
Author-email: enikita332@gmail.com
Requires-Python: >=3.11,<4.0
Classifier: Programming Language :: Python :: 3
Classifier: Programming Language :: Python :: 3.11
Classifier: Programming Language :: Python :: 3.12
Requires-Dist: rich (>=13.7.0,<14.0.0)
